ifnude/__init__.py
ifnude/detector.py
ifnude/detector_utils.py
ifnude/image_utils.py
ifnude-0.0.3.dist-info/LICENSE.md
ifnude-0.0.3.dist-info/METADATA
ifnude-0.0.3.dist-info/WHEEL
ifnude-0.0.3.dist-info/top_level.txt
ifnude-0.0.3.dist-info/RECORD
