Metadata-Version: 2.1
Name: ifnude
Version: 0.0.3
Summary: An AI powered nudity detection library
Home-page: https://github.com/s0md3v/ifnude
Author: Somdev Sangwan
Author-email: s0md3v@gmail.com
License: GPLv3
Classifier: License :: OSI Approved :: GNU General Public License v3 (GPLv3)
Classifier: Programming Language :: Python
Classifier: Programming Language :: Python :: 3
Classifier: Programming Language :: Python :: 3.6
Classifier: Programming Language :: Python :: Implementation :: CPython
Classifier: Programming Language :: Python :: Implementation :: PyPy
Requires-Python: >=3.6.0
License-File: LICENSE.md
Requires-Dist: pillow
Requires-Dist: opencv-python-headless (>=4.5.1.48)
Requires-Dist: tqdm
Requires-Dist: scikit-image
Requires-Dist: onnxruntime
